smart_router_api/__init__.py
smart_router_api/router_status.py
smart_router_api-1.1.1.dist-info/DESCRIPTION.rst
smart_router_api-1.1.1.dist-info/METADATA
smart_router_api-1.1.1.dist-info/RECORD
smart_router_api-1.1.1.dist-info/WHEEL
smart_router_api-1.1.1.dist-info/metadata.json
smart_router_api-1.1.1.dist-info/top_level.txt
