Metadata-Version: 2.0
Name: smart-router-api
Version: 1.1.1
Summary: smart router of api
Home-page: UNKNOWN
Author: freedomDR
Author-email: 1640145602@qq.com
License: MIT
Platform: UNKNOWN
